{"files":{"index.html":{"frameworks":["pg.insight.events","pg.css.grid","pg.image.overlay","pg.code-validator","pg.project.items","pg.asset.manager","bs4","pg.html","pg.components"],"last_page_width":1024},"2018.html":{"frameworks":["eyounx.github.io.git","pg.insight.events","pg.css.grid","pg.image.overlay","pg.code-validator","pg.project.items","pg.asset.manager","foundation.6.4.3","pg.html","pg.components"],"last_page_width":1024}},"breakpoints":["576px","768px","992px","1200px"],"frameworks":["eyounx.github.io.git","pg.insight.events","pg.css.grid","pg.image.overlay","pg.code-validator","pg.project.items","pg.asset.manager","foundation.6.4.3","pg.html","pg.components"],"template_framework_id":"bootstrap","cs-for-overrides":"style.css"}